{"preferences":[{"id":1,"title":"Smoking","identifier":"smoking_01","option":"Yes","checked":false}],"vehicle_type":["Coupe","Hatchback","Micro","Mini SUV","Mini Van","Roadster","Sedan","SUV","Van"],"min_estimate":0.125,"max_estimate":0.25,"reference_source":["Campus Event","Facebook","Friend\/Family","Instagram","Student Ambassador","Student Organization","Youtube","Other"],"make":[{"name":"Acura","models":["2.2CL","2.3CL","2.5TL","3.0CL","3.2CL","3.2TL","3.5 RL","CL Models (4)","ILX","Integra","Legend","MDX","NSX","Other Acura Models","RDX","RL","RL Models (2)","RSX","SLX","TL","TL Models (3)","TSX","Vigor","ZDX"]},{"name":"Alfa Romeo","models":["164","8C Competizione","GTV-6","Milano","Other Alfa Romeo Models","Spider"]},{"name":"AMC","models":["Alliance","Concord","Eagle","Encore","Other AMC Models","Spirit"]},{"name":"Audi","models":["100","200","4000","5000","80","90","A3","A4","A5","A6","A7","A8","allroad","Cabriolet","Coupe","Other Audi Models","Q3","Q5","Q7","Quattro","R8","RS 4","RS 5","RS 6","S4","S5","S6","S7","S8","TT","TT RS","TTS","V8 Quattro"]},{"name":"Avanti","models":["Convertible","Coupe","Other Avanti Models","Sedan"]},{"name":"BMW","models":["1 Series (3)","1 Series M","128i","135i","135is","3 Series (29)","318i","318iC","318iS","318ti","320i","323ci","323i","323is","323iT","325","325Ci","325e","325es","325i","325is","325iX","325xi","328Ci","328i","328iS","328xi","330Ci","330i","330xi","335d","335i","335is","335xi","5 Series (19)","524td","525i","525xi","528e","528i","528iT","528xi","530i","530iT","530xi","533i","535i","535i Gran Turismo","535xi","540i","545i","550i","550i Gran Turismo","6 Series (8)","633CSi","635CSi","640i","640i Gran Coupe","645Ci","650i","650i Gran Coupe","7 Series (15)","733i","735i","735iL","740i","740iL","740Li","745i","745Li","750i","750iL","750Li","760i","760Li","8 Series (4)","840Ci","850Ci","850CSi","850i","ActiveHybrid 3","ActiveHybrid 5","ActiveHybrid 7","ActiveHybrid X6","Alpina B7","L Series (1)","L6","L7","M Coupe","M Roadster","M Series (8)","M3","M5","M6","Other BMW Models","X Series (5)","X1","X3","X5","X5 M","X6","X6 M","Z Series (3)","Z3","Z4","Z8"]},{"name":"Buick","models":["Century","Electra","Enclave","Encore","LaCrosse","Le Sabre","Lucerne","Other Buick Models","Park Avenue","Rainier","Reatta","Regal","Rendezvous","Riviera","Roadmaster","Skyhawk","Skylark","Somerset","Terraza","Verano"]},{"name":"Cadillac","models":["Allante","ATS","Brougham","Catera","Cimarron","CTS","De Ville","DTS","Eldorado","Escalade","Escalade ESV","Escalade EXT","Fleetwood","Other Cadillac Models","Seville","SRX","STS","XLR","XTS"]},{"name":"Chevrolet","models":["Astro","Avalanche","Aveo","Aveo5","Beretta","Blazer","Camaro","Caprice","Captiva Sport","Cavalier","Celebrity","Chevette","Citation","Cobalt","Colorado","Corsica","Corvette","Cruze","El Camino","Equinox","Express Van","G Van","HHR","Impala","Kodiak C4500","Lumina","Lumina APV","LUV","Malibu","Metro","Monte Carlo","Nova","Other Chevrolet Models","Prizm","S10 Blazer","S10 Pickup","Silverado and other C\/K1500","Silverado and other C\/K2500","Silverado and other C\/K3500","Sonic","Spark","Spectrum","Sprint","SSR","Suburban","Tahoe","Tracker","TrailBlazer","TrailBlazer EXT","Traverse","Uplander","Venture","Volt"]},{"name":"Chrysler","models":["200","300","300M","Aspen","Caravan","Cirrus","Concorde","Conquest","Cordoba","Crossfire","E Class","Fifth Avenue","Grand Voyager","Imperial","Intrepid","Laser","LeBaron","LHS","Neon","New Yorker","Newport","Other Chrysler Models","Pacifica","Prowler","PT Cruiser","Sebring","TC by Maserati","Town &amp; Country","Voyager"]},{"name":"Daewoo","models":["Lanos","Leganza","Nubira","Other Daewoo Models"]},{"name":"Daihatsu","models":["Charade","Other Daihatsu Models","Rocky"]},{"name":"Datsun","models":["200SX","210","280ZX","300ZX","310","510","720","810","Maxima","Other Datsun Models","Pickup","Pulsar","Sentra","Stanza"]},{"name":"Dodge","models":["400","600","Aries","Avenger","Caliber","Caravan","Challenger","Charger","Colt","Conquest","D\/W Truck","Dakota","Dart","Daytona","Diplomat","Durango","Dynasty","Grand Caravan","Intrepid","Journey","Lancer","Magnum","Mirada","Monaco","Neon","Nitro","Omni","Other Dodge Models","Raider","Ram 1500 Truck","Ram 2500 Truck","Ram 3500 Truck","Ram 4500 Truck","Ram 50 Truck","RAM C\/V","Ram SRT-10","Ram Van","Ram Wagon","Ramcharger","Rampage","Shadow","Spirit","Sprinter","SRT-4","St. Regis","Stealth","Stratus","Viper"]},{"name":"Eagle","models":["Medallion","Other Eagle Models","Premier","Summit","Talon","Vision"]},{"name":"FIAT","models":["2000 Spider","500","Bertone X1\/9","Brava","Other Fiat Models","Pininfarina Spider","Strada","X1\/9"]},{"name":"Fisker","models":["Karma"]},{"name":"Ford","models":["Aerostar","Aspire","Bronco","Bronco II","C-MAX","Club Wagon","Contour","Courier","Crown Victoria","E-150 and Econoline 150","E-250 and Econoline 250","E-350 and Econoline 350","Edge","Escape","Escort","Excursion","EXP","Expedition","Expedition EL","Explorer","Explorer Sport Trac","F100","F150","F250","F350","F450","Fairmont","Festiva","Fiesta","Five Hundred","Flex","Focus","Freestar","Freestyle","Fusion","Granada","GT","LTD","Mustang","Other Ford Models","Probe","Ranger","Taurus","Taurus X","Tempo","Thunderbird","Transit Connect","Windstar","ZX2 Escort"]},{"name":"Freightliner","models":["Sprinter"]},{"name":"Geo","models":["Metro","Other Geo Models","Prizm","Spectrum","Storm","Tracker"]},{"name":"GMC","models":["Acadia","Caballero","Canyon","Envoy","Envoy XL","Envoy XUV","Jimmy","Other GMC Models","Rally Wagon","S15 Jimmy","S15 Pickup","Safari","Savana","Sierra C\/K1500","Sierra C\/K2500","Sierra C\/K3500","Sonoma","Suburban","Syclone","Terrain","TopKick C4500","Typhoon","Vandura","Yukon","Yukon XL"]},{"name":"Honda","models":["Accord","Accord Crosstour","Civic","CR-V","CR-Z","Crosstour","Crosstour and Accord Crosstour Models (2)","CRX","Del Sol","Element","Fit","Insight","Odyssey","Other Honda Models","Passport","Pilot","Prelude","Ridgeline","S2000"]},{"name":"HUMMER","models":["H1","H2","H3","H3T","Other Hummer Models"]},{"name":"Hyundai","models":["Accent","Azera","Elantra","Elantra Coupe","Elantra Touring","Entourage","Equus","Excel","Genesis","Genesis Coupe","Other Hyundai Models","Santa Fe","Scoupe","Sonata","Tiburon","Tucson","Veloster","Veracruz","XG300","XG350"]},{"name":"Infiniti","models":["EX Models (2)","EX35","EX37","FX Models (4)","FX35","FX37","FX45","FX50","G Models (4)","G20","G25","G35","G37","I Models (2)","I30","I35","J Models (1)","J30","JX Models (1)","JX35","M Models (6)","M30","M35","M35h","M37","M45","M56","Other Infiniti Models","Q Models (1)","Q45","QX Models (2)","QX4","QX56"]},{"name":"Isuzu","models":["Amigo","Ascender","Axiom","Hombre","i-280","i-290","i-350","i-370","I-Mark","Impulse","Oasis","Other Isuzu Models","Pickup","Rodeo","Stylus","Trooper","Trooper II","VehiCROSS"]},{"name":"Jaguar","models":["Other Jaguar Models","S-Type","X-Type","XF","XJ","XJ Series (10)","XJ Sport","XJ Vanden Plas","XJ12","XJ6","XJ8","XJ8 L","XJR","XJR-S","XJS","XK","XK Series (3)","XK8","XKR"]},{"name":"Jeep","models":["Cherokee","CJ","Comanche","Commander","Compass","Grand Cherokee","Grand Wagoneer","Liberty","Other Jeep Models","Patriot","Pickup","Scrambler","Wagoneer","Wrangler"]},{"name":"Kia","models":["Amanti","Borrego","Forte","Forte Koup","Optima","Other Kia Models","Rio","Rio5","Rondo","Sedona","Sephia","Sorento","Soul","Spectra","Spectra5","Sportage"]},{"name":"Lancia","models":["Beta","Other Lancia Models","Zagato"]},{"name":"Land Rover","models":["Defender","Discovery","Freelander","LR2","LR3","LR4","Other Land Rover Models","Range Rover","Range Rover Evoque","Range Rover Sport"]},{"name":"Lexus","models":["CT 200h","CT Models (1)","ES 250","ES 300","ES 300h","ES 330","ES 350","ES Models (5)","GS 300","GS 350","GS 400","GS 430","GS 450h","GS 460","GS Models (6)","GX 460","GX 470","GX Models (2)","HS 250h","HS Models (1)","IS 250","IS 250C","IS 300","IS 350","IS 350C","IS F","IS Models (6)","LFA","LS 400","LS 430","LS 460","LS 600h","LS Models (4)","LX 450","LX 470","LX 570","LX Models (3)","Other Lexus Models","RX 300","RX 330","RX 350","RX 400h","RX 450h","RX Models (5)","SC 300","SC 400","SC 430","SC Models (3)"]},{"name":"Lincoln","models":["Aviator","Blackwood","Continental","LS","Mark LT","Mark VI","Mark VII","Mark VIII","MKS","MKT","MKX","MKZ","Navigator","Navigator L","Other Lincoln Models","Town Car","Zephyr"]},{"name":"Lotus","models":["Elan","Elise","Esprit","Evora","Exige","Other Lotus Models"]},{"name":"Maserati","models":["430","Biturbo","Coupe","GranSport","GranTurismo","Other Maserati Models","Quattroporte","Spyder"]},{"name":"Maybach","models":["57","62","Other Maybach Models"]},{"name":"Mazda","models":["323","626","929","B-Series Pickup","CX-5","CX-7","CX-9","GLC","MAZDA2","MAZDA3","MAZDA5","MAZDA6","MAZDASPEED3","MAZDASPEED6","Miata MX5","Millenia","MPV","MX3","MX6","Navajo","Other Mazda Models","Protege","Protege5","RX-7","RX-8","Tribute"]},{"name":"McLaren","models":["MP4-12C"]},{"name":"Mercedes-Benz","models":["190 Class (2)","190D","190E","240 Class (1)","240D","260E","280CE","280E","300 Class \/ E Class (6)","300CD","300CE","300D","300E","300SD","300SDL","300SE","300SEL","300SL","300TD","300TE","350SD","350SDL","380SE","380SEC","380SEL","380SL","380SLC","400E","400SE","400SEL","420SEL","500E","500SEC","500SEL","500SL","560SEC","560SEL","560SL","600SEC","600SEL","600SL","C Class (13)","C220","C230","C240","C250","C280","C300","C32 AMG","C320","C350","C36 AMG","C43 AMG","C55 AMG","C63 AMG","CL Class (6)","CL500","CL55 AMG","CL550","CL600","CL63 AMG","CL65 AMG","CLK Class (7)","CLK320","CLK350","CLK430","CLK500","CLK55 AMG","CLK550","CLK63 AMG","CLS Class (4)","CLS500","CLS55 AMG","CLS550","CLS63 AMG","E Class (18)","E300","E320","E320 Bluetec","E320 CDI","E350","E350 Bluetec","E400 Hybrid","E420","E430","E500","E55 AMG","E550","E63 AMG","G Class (4)","G500","G55 AMG","G550","G63 AMG","GL Class (5)","GL320 Bluetec","GL320 CDI","GL350 Bluetec","GL450","GL550","GLK Class (1)","GLK350","M Class (11)","ML320","ML320 Bluetec","ML320 CDI","ML350","ML350 Bluetec","ML430","ML450 Hybrid","ML500","ML55 AMG","ML550","ML63 AMG","Other Mercedes-Benz Models","R Class (6)","R320 Bluetec","R320 CDI","R350","R350 Bluetec","R500","R63 AMG","S Class (30)","S320","S350","S350 Bluetec","S400 Hybrid","S420","S430","S500","S55 AMG","S550","S600","S63 AMG","S65 AMG","SL Class (13)","SL320","SL500","SL55 AMG","SL550","SL600","SL63 AMG","SL65 AMG","SLK Class (8)","SLK230","SLK250","SLK280","SLK300","SLK32 AMG","SLK320","SLK350","SLK55 AMG","SLR","SLR Class (1)","SLS AMG","SLS Class (1)","Sprinter","Sprinter Class (1)"]},{"name":"Mercury","models":["Capri","Cougar","Grand Marquis","Lynx","Marauder","Mariner","Marquis","Milan","Montego","Monterey","Mountaineer","Mystique","Other Mercury Models","Sable","Topaz","Tracer","Villager","Zephyr"]},{"name":"Merkur","models":["Other Merkur Models","Scorpio","XR4Ti"]},{"name":"MINI","models":["Cooper","Cooper Clubman","Cooper Clubman Models (2)","Cooper Countryman","Cooper Countryman Models (2)","Cooper Coupe","Cooper Coupe Models (2)","Cooper Models (2)","Cooper Roadster","Cooper Roadster Models (2)","Cooper S","Cooper S Clubman","Cooper S Countryman","Cooper S Coupe","Cooper S Roadster"]},{"name":"Mitsubishi","models":["3000GT","Cordia","Diamante","Eclipse","Endeavor","Expo","Galant","i","Lancer","Lancer Evolution","Mighty Max","Mirage","Montero","Montero Sport","Other Mitsubishi Models","Outlander","Outlander Sport","Precis","Raider","Sigma","Starion","Tredia","Van"]},{"name":"Nissan","models":["200SX","240SX","300ZX","350Z","370Z","Altima","Armada","Axxess","Cube","Frontier","GT-R","Juke","Leaf","Maxima","Murano","Murano CrossCabriolet","NV","NX","Other Nissan Models","Pathfinder","Pickup","Pulsar","Quest","Rogue","Sentra","Stanza","Titan","Van","Versa","Xterra"]},{"name":"Oldsmobile","models":["88","Achieva","Alero","Aurora","Bravada","Custom Cruiser","Cutlass","Cutlass Calais","Cutlass Ciera","Cutlass Supreme","Firenza","Intrigue","Ninety-Eight","Omega","Other Oldsmobile Models","Regency","Silhouette","Toronado"]},{"name":"Peugeot","models":["405","504","505","604","Other Peugeot Models"]},{"name":"Plymouth","models":["Acclaim","Arrow","Breeze","Caravelle","Champ","Colt","Conquest","Gran Fury","Grand Voyager","Horizon","Laser","Neon","Other Plymouth Models","Prowler","Reliant","Sapporo","Scamp","Sundance","Trailduster","Voyager"]},{"name":"Pontiac","models":["1000","6000","Aztek","Bonneville","Catalina","Fiero","Firebird","G3","G5","G6","G8","Grand Am","Grand Prix","GTO","J2000","Le Mans","Montana","Other Pontiac Models","Parisienne","Phoenix","Safari","Solstice","Sunbird","Sunfire","Torrent","Trans Sport","Vibe"]},{"name":"RAM","models":["1500","2500","3500","4500"]},{"name":"Renault","models":["18i","Fuego","Le Car","Other Renault Models","R18","Sportwagon"]},{"name":"Saab","models":["9-2X","9-3","9-4X","9-5","9-7X","900","9000","Other Saab Models"]},{"name":"Saturn","models":["Astra","Aura","ION","L Series (3)","L100","L200","L300","LS","LW Series (4)","LW1","LW2","LW200","LW300","Other Saturn Models","Outlook","Relay","SC Series (2)","SC1","SC2","Sky","SL","SL Series (3)","SL1","SL2","SW Series (2)","SW1","SW2","Vue"]},{"name":"Scion","models":["FR-S","iQ","tC","xA","xB","xD"]},{"name":"smart","models":["fortwo","Other smart Models"]},{"name":"SRT","models":["Viper"]},{"name":"Sterling","models":["825","827","Other Sterling Models"]},{"name":"Subaru","models":["Baja","Brat","BRZ","Forester","Impreza","Impreza WRX","Justy","L Series","Legacy","Loyale","Other Subaru Models","Outback","SVX","Tribeca","XT","XV Crosstrek"]},{"name":"Suzuki","models":["Aerio","Equator","Esteem","Forenza","Grand Vitara","Kizashi","Other Suzuki Models","Reno","Samurai","Sidekick","Swift","SX4","Verona","Vitara","X-90","XL7"]},{"name":"Tesla","models":["Roadster"]},{"name":"Toyota","models":["4Runner","Avalon","Camry","Celica","Corolla","Corona","Cressida","Echo","FJ Cruiser","Highlander","Land Cruiser","Matrix","MR2","MR2 Spyder","Other Toyota Models","Paseo","Pickup","Previa","Prius","Prius C","Prius V","RAV4","Sequoia","Sienna","Solara","Starlet","Supra","T100","Tacoma","Tercel","Tundra","Van","Venza","Yaris"]},{"name":"Triumph","models":["Other Triumph Models","TR7","TR8"]},{"name":"Volkswagen","models":["Beetle","Cabrio","Cabriolet","CC","Corrado","Dasher","Eos","Eurovan","Fox","GLI","Golf","Golf and Rabbit Models (2)","Golf R","GTI","Jetta","Other Volkswagen Models","Passat","Phaeton","Pickup","Quantum","R32","Rabbit","Routan","Scirocco","Tiguan","Touareg","Vanagon"]},{"name":"Volvo","models":["240","260","740","760","780","850","940","960","C30","C70","Other Volvo Models","S40","S60","S70","S80","S90","V40","V50","V70","V90","XC60","XC70","XC90"]},{"name":"Yugo","models":["GV","GVC","GVL","GVS","GVX","Other Yugo Models"]}]}